abs_nosql_repository_core/__init__.py
abs_nosql_repository_core/document/__init__.py
abs_nosql_repository_core/document/base_document.py
abs_nosql_repository_core/repository/__init__.py
abs_nosql_repository_core/repository/base_collection_repository.py
abs_nosql_repository_core/repository/base_repository.py
abs_nosql_repository_core/schema/__init__.py
abs_nosql_repository_core/schema/base_collection_schema.py
abs_nosql_repository_core/schema/base_schema.py
abs_nosql_repository_core/service/__init__.py
abs_nosql_repository_core/service/base_collection_service.py
abs_nosql_repository_core/service/base_service.py
abs_nosql_repository_core/util/__init__.py
abs_nosql_repository_core/util/coerce_value.py
abs_nosql_repository_core/util/date_utils.py
abs_nosql_repository_core/util/operator_mappings.py
abs_nosql_repository_core/util/type_conversion.py
abs_nosql_repository_core-0.11.11.dist-info/METADATA
abs_nosql_repository_core-0.11.11.dist-info/WHEEL
abs_nosql_repository_core-0.11.11.dist-info/RECORD
