Metadata-Version: 2.3
Name: abs-nosql-repository-core
Version: 0.11.11
Summary: Shared base repository and service utilities for Beanie(NoSQL)-backed FastAPI apps.
License: MIT
Author: AutoBridgeSystems
Author-email: info@autobridgesystems.com
Requires-Python: >=3.11,<4.0
Classifier: License :: OSI Approved :: MIT License
Classifier: Programming Language :: Python :: 3
Classifier: Programming Language :: Python :: 3.11
Classifier: Programming Language :: Python :: 3.12
Classifier: Programming Language :: Python :: 3.13
Requires-Dist: abs-exception-core (>=0.2.0,<0.3.0)
Requires-Dist: abs-utils (>=0.4.1,<0.5.0)
Requires-Dist: beanie (>=1.29.0,<2.0.0)
Requires-Dist: fastapi[standard] (>=0.115.12,<0.116.0)
